<?xml version="1.0" encoding="utf-8"?>
<!DOCTYPE task PUBLIC "-//OASIS//DTD DITA Task//EN"
  "../../dtd/task.dtd">
<task id="setting-to" xml:lang="en-us">
  <title>Setting <codeph>To:</codeph> Recipients</title>
  <shortdesc>
    <codeph>To:</codeph> recipients are required in a message and are set with the
    <codeph>setTo()</codeph> method of the message.
  </shortdesc>
  <prolog>
    <author type="creator">Chris Corbyn</author>
    <copyright>
      <copyryear year="2008"/>
      <copyrholder>Chris Corbyn</copyrholder>
    </copyright>
    <critdates>
      <created date="2008-December-26"/>
      <revised modified="2008-December-26"/>
    </critdates>
    <metadata>
      <keywords>
        <keyword>swift mailer</keyword>
        <keyword>php</keyword>
        <keyword>message</keyword>
        <keyword>to recipients</keyword>
        <indexterm>
          messages
          <indexterm>recipients</indexterm>
        </indexterm>
      </keywords>
    </metadata>
  </prolog>
  <taskbody>
    <context>
      <p>
        To set <codeph>To:</codeph> recipients:
      </p>
    </context>
    <steps-unordered>
      <step>
        <cmd>
          Call the <codeph>setTo()</codeph> method on the Message.
        </cmd>
      </step>
    </steps-unordered>
    
    <result>
      <p>
        <codeph>To:</codeph> recipients are visible in the message headers and will
        be seen by the other recipients.
      </p>
      <note>
        You should also use the <codeph>setTo()</codeph> method when you want to perform
        a <codeph>batchSend()</codeph> to deliver the message to each recipient separately
        without exposing all of the addresses.  In this scenario Swift Mailer performs
        some internal transformations on the message during the sending process.
      </note>
    </result>
    
    <example id="setto">
<codeblock><![CDATA[
$message->setTo(array(
  'person1@example.org',
  'person2@otherdomain.org' => 'Person 2 Name',
  'person3@example.org',
  'person4@example.org',
  'person5@example.org' => 'Person 5 Name'
));
]]></codeblock>
    </example>
    
  </taskbody>
</task>
